fsdp2_utils/__init__.py
fsdp2_utils/py.typed
fsdp2_utils/fully_shard/__init__.py
fsdp2_utils/fully_shard/apply.py
fsdp2_utils/fully_shard/types.py
fsdp2_utils/tensor_parallel/__init__.py
fsdp2_utils/tensor_parallel/apply.py
fsdp2_utils/tensor_parallel/parallelize.py
fsdp2_utils/tensor_parallel/plan.py
fsdp2_utils/tensor_parallel/types.py
fsdp2_utils/tensor_parallel/parallel_style/__init__.py
fsdp2_utils/tensor_parallel/parallel_style/prepare_module.py
fsdp2_utils/tensor_parallel/parallel_style/rowwise_parallel.py
fsdp2_utils/tensor_parallel/parallel_style/sequence_parallel.py
fsdp2_utils-0.1.1.dist-info/METADATA
fsdp2_utils-0.1.1.dist-info/WHEEL
fsdp2_utils-0.1.1.dist-info/RECORD
